MANIFEST.in
Makefile
README.rst
requirements.txt
requirements_test.txt
setup.py
tox.ini
steamfiles/__init__.py
steamfiles/__main__.py
steamfiles/acf.py
steamfiles/appinfo.py
steamfiles/manifest.py
steamfiles/manifest_pb2.py
steamfiles.egg-info/PKG-INFO
steamfiles.egg-info/SOURCES.txt
steamfiles.egg-info/dependency_links.txt
steamfiles.egg-info/requires.txt
steamfiles.egg-info/top_level.txt