Metadata-Version: 1.1
Name: steamfiles
Version: 0.1.4
Summary: Python library for parsing the most common Steam file formats.
Home-page: https://github.com/leovp/steamfiles
Author: Leonid Runyshkin
Author-email: runyshkin@gmail.com
License: MIT
Keywords: steam files valve format parse appinfo vdf acf manifest
Platform: any
Classifier: Development Status :: 4 - Beta
Classifier: Intended Audience :: Developers
Classifier: License :: OSI Approved :: MIT License
Classifier: Operating System :: OS Independent
Classifier: Topic :: Software Development :: Libraries
Classifier: Topic :: Software Development :: Libraries :: Python Modules
Classifier: Topic :: Utilities
Classifier: Programming Language :: Python
Classifier: Programming Language :: Python :: 3
Classifier: Programming Language :: Python :: 3.5
Classifier: Programming Language :: Python :: 3.6
Classifier: Programming Language :: Python :: 3.7
Classifier: Programming Language :: Python :: 3.8
